eventeditor/__init__.py
eventeditor/__main__.py
eventeditor/_version.py
eventeditor/actor_json.py
eventeditor/actor_model.py
eventeditor/actor_string_list_model.py
eventeditor/actor_string_list_view.py
eventeditor/actor_view.py
eventeditor/ai.py
eventeditor/autosave.py
eventeditor/container_model.py
eventeditor/container_view.py
eventeditor/data_editors.py
eventeditor/entry_point_model.py
eventeditor/event_branch_editors.py
eventeditor/event_chooser_dialog.py
eventeditor/event_edit_dialog.py
eventeditor/event_fork_chooser_dialog.py
eventeditor/event_model.py
eventeditor/event_view.py
eventeditor/flow_data.py
eventeditor/flowchart_tools.py
eventeditor/flowchart_view.py
eventeditor/search_bar.py
eventeditor/util.py
eventeditor/assets/index.html
eventeditor/assets/main.css
eventeditor/assets/main.js
eventeditor/assets/lib/d3.v3.min.js
eventeditor/assets/lib/dagre-d3.js
eventeditor/assets/lib/graphlib.min.js
eventeditor/assets/lib/package-lock.json
eventeditor/assets/lib/node_modules/d3-context-menu/.npmignore
eventeditor/assets/lib/node_modules/d3-context-menu/LICENSE.txt
eventeditor/assets/lib/node_modules/d3-context-menu/README.md
eventeditor/assets/lib/node_modules/d3-context-menu/bower.json
eventeditor/assets/lib/node_modules/d3-context-menu/package.json
eventeditor/assets/lib/node_modules/d3-context-menu/css/d3-context-menu.css
eventeditor/assets/lib/node_modules/d3-context-menu/examples/index.htm
eventeditor/assets/lib/node_modules/d3-context-menu/js/d3-context-menu.js
eventeditor-1.3.9.post1.dist-info/LICENSE
eventeditor-1.3.9.post1.dist-info/METADATA
eventeditor-1.3.9.post1.dist-info/WHEEL
eventeditor-1.3.9.post1.dist-info/entry_points.txt
eventeditor-1.3.9.post1.dist-info/top_level.txt
eventeditor-1.3.9.post1.dist-info/RECORD
